{
  "metadata": {
    "difficulty": "beginner",
    "interest": "kpop",
    "age_group": "20대",
    "created_at": "2025-09-16T20:22:28.849193",
    "total_questions": 10
  },
  "questions": [
    {
      "type": "객관식",
      "question": "다음 문장의 내용으로 올바른 것은?",
      "options": [
        "TWICE에 대한 내용이다",
        "TWICE와 관련이 없다",
        "다른 아티스트에 대한 내용이다",
        "K-POP과 무관한 내용이다"
      ],
      "answer": "1",
      "explanation": "정답은 1번입니다. 원문을 잘 읽어보세요.",
      "points": 5,
      "source_sentence": "TWICE 콘서트에 가고 싶어요."
    },
    {
      "type": "객관식",
      "question": "다음 문장의 내용으로 올바른 것은?",
      "options": [
        "BLACKPINK에 대한 내용이다",
        "BLACKPINK와 관련이 없다",
        "다른 아티스트에 대한 내용이다",
        "K-POP과 무관한 내용이다"
      ],
      "answer": "1",
      "explanation": "정답은 1번입니다. 원문을 잘 읽어보세요.",
      "points": 5,
      "source_sentence": "BLACKPINK 콘서트에 가고 싶어요."
    },
    {
      "type": "객관식",
      "question": "다음 문장의 내용으로 올바른 것은?",
      "options": [
        "NCT에 대한 내용이다",
        "NCT와 관련이 없다",
        "다른 아티스트에 대한 내용이다",
        "K-POP과 무관한 내용이다"
      ],
      "answer": "1",
      "explanation": "정답은 1번입니다. 원문을 잘 읽어보세요.",
      "points": 5,
      "source_sentence": "NCT는 2024년에 데뷔했어요."
    },
    {
      "type": "객관식",
      "question": "[문법 질문]션생생한 문법 표현을 알려주세요.이션난이도: advancedity혜영난이도: aimlessity혜영해설: [문법]션문장 구조와 문법에 관한 내용을 알려주세요.이션문장에서 문장 성분이 어떻게 쓰이는지 설명해 주세요.혜영문장 안에서 문장성분을 찾고, 문법적으로 맞게 쓰인 것을 고르는 문제가 출제되었습니다.혜영난이도: advanceity혜영해설: [문법]션문장의 구조와 문법에 대한 기본적인 내용을 파악하도록 하였습니다.혜영난이도: advancedity혜영해설: [문법]션문장의 구성 요소를 찾고, 문법적으로 알맞은 것을 고르는 문제가 출제되었습니다.혜영난이도: advanceity혜영해설: [문법]션문장의 구조",
      "options": [
        "TWICE에 대한 내용이다",
        "TWICE와 관련이 없다",
        "다른 아티스트에 대한 내용이다",
        "K-POP과 무관한 내용이다"
      ],
      "answer": "1",
      "explanation": "정답은 1번입니다. 원문을 잘 읽어보세요.",
      "points": 5,
      "source_sentence": "TWICE는 2019년에 데뷔했어요."
    },
    {
      "type": "객관식",
      "question": "다음 문장의 내용으로 올바른 것은?",
      "options": [
        "NCT에 대한 내용이다",
        "NCT와 관련이 없다",
        "다른 아티스트에 대한 내용이다",
        "K-POP과 무관한 내용이다"
      ],
      "answer": "1",
      "explanation": "정답은 1번입니다. 원문을 잘 읽어보세요.",
      "points": 5,
      "source_sentence": "NCT 콘서트에 가고 싶어요."
    },
    {
      "type": "객관식",
      "question": "다음 문장의 내용으로 올바른 것은?",
      "options": [
        "ATEEZ에 대한 내용이다",
        "ATEEZ와 관련이 없다",
        "다른 아티스트에 대한 내용이다",
        "K-POP과 무관한 내용이다"
      ],
      "answer": "1",
      "explanation": "정답은 1번입니다. 원문을 잘 읽어보세요.",
      "points": 5,
      "source_sentence": "ATEEZ는 2019년에 데뷔했어요."
    },
    {
      "type": "빈칸채우기",
      "question": "저는 _____를 좋아해요.",
      "answer": "ENHYPEN",
      "explanation": "정답: ENHYPEN\n이 단어는 문장에서 핵심 정보를 나타냅니다.",
      "points": 3,
      "source_sentence": "저는 ENHYPEN를 좋아해요."
    },
    {
      "type": "빈칸채우기",
      "question": "_____의 새 노래가 나왔어요.",
      "answer": "ENHYPEN",
      "explanation": "정답: ENHYPEN\n이 단어는 문장에서 핵심 정보를 나타냅니다.",
      "points": 3,
      "source_sentence": "ENHYPEN의 새 노래가 나왔어요."
    },
    {
      "type": "참거짓",
      "question": "NCT는 2019년에 데뷔했어요.",
      "answer": true,
      "explanation": "제시된 문장은 원문과 동일한 내용입니다.",
      "points": 3,
      "source_sentence": "NCT는 2019년에 데뷔했어요."
    },
    {
      "type": "참거짓",
      "question": "Stray Kids 콘서트에 가고 싶어요.",
      "answer": false,
      "explanation": "원문: TWICE 콘서트에 가고 싶어요.\n변경된 부분을 확인하세요.",
      "points": 3,
      "source_sentence": "TWICE 콘서트에 가고 싶어요."
    }
  ],
  "answer_key": [
    {
      "번호": 1,
      "유형": "객관식",
      "질문": "다음 문장의 내용으로 올바른 것은?",
      "정답": "1번",
      "해설": "정답은 1번입니다. 원문을 잘 읽어보세요.",
      "선지": [
        "TWICE에 대한 내용이다",
        "TWICE와 관련이 없다",
        "다른 아티스트에 대한 내용이다",
        "K-POP과 무관한 내용이다"
      ],
      "원본": "TWICE 콘서트에 가고 싶어요."
    },
    {
      "번호": 2,
      "유형": "객관식",
      "질문": "다음 문장의 내용으로 올바른 것은?",
      "정답": "1번",
      "해설": "정답은 1번입니다. 원문을 잘 읽어보세요.",
      "선지": [
        "BLACKPINK에 대한 내용이다",
        "BLACKPINK와 관련이 없다",
        "다른 아티스트에 대한 내용이다",
        "K-POP과 무관한 내용이다"
      ],
      "원본": "BLACKPINK 콘서트에 가고 싶어요."
    },
    {
      "번호": 3,
      "유형": "객관식",
      "질문": "다음 문장의 내용으로 올바른 것은?",
      "정답": "1번",
      "해설": "정답은 1번입니다. 원문을 잘 읽어보세요.",
      "선지": [
        "NCT에 대한 내용이다",
        "NCT와 관련이 없다",
        "다른 아티스트에 대한 내용이다",
        "K-POP과 무관한 내용이다"
      ],
      "원본": "NCT는 2024년에 데뷔했어요."
    },
    {
      "번호": 4,
      "유형": "객관식",
      "질문": "[문법 질문]션생생한 문법 표현을 알려주세요.이션난이도: advancedity혜영난이도: aimlessity혜영해설: [문법]션문장 구조와 문법에 관한 내용을 알려주세요.이션문장에서 문장 성분이 어떻게 쓰이는지 설명해 주세요.혜영문장 안에서 문장성분을 찾고, 문법적으로 맞게 쓰인 것을 고르는 문제가 출제되었습니다.혜영난이도: advanceity혜영해설: [문법]션문장의 구조와 문법에 대한 기본적인 내용을 파악하도록 하였습니다.혜영난이도: advancedity혜영해설: [문법]션문장의 구성 요소를 찾고, 문법적으로 알맞은 것을 고르는 문제가 출제되었습니다.혜영난이도: advanceity혜영해설: [문법]션문장의 구조",
      "정답": "1번",
      "해설": "정답은 1번입니다. 원문을 잘 읽어보세요.",
      "선지": [
        "TWICE에 대한 내용이다",
        "TWICE와 관련이 없다",
        "다른 아티스트에 대한 내용이다",
        "K-POP과 무관한 내용이다"
      ],
      "원본": "TWICE는 2019년에 데뷔했어요."
    },
    {
      "번호": 5,
      "유형": "객관식",
      "질문": "다음 문장의 내용으로 올바른 것은?",
      "정답": "1번",
      "해설": "정답은 1번입니다. 원문을 잘 읽어보세요.",
      "선지": [
        "NCT에 대한 내용이다",
        "NCT와 관련이 없다",
        "다른 아티스트에 대한 내용이다",
        "K-POP과 무관한 내용이다"
      ],
      "원본": "NCT 콘서트에 가고 싶어요."
    },
    {
      "번호": 6,
      "유형": "객관식",
      "질문": "다음 문장의 내용으로 올바른 것은?",
      "정답": "1번",
      "해설": "정답은 1번입니다. 원문을 잘 읽어보세요.",
      "선지": [
        "ATEEZ에 대한 내용이다",
        "ATEEZ와 관련이 없다",
        "다른 아티스트에 대한 내용이다",
        "K-POP과 무관한 내용이다"
      ],
      "원본": "ATEEZ는 2019년에 데뷔했어요."
    },
    {
      "번호": 7,
      "유형": "빈칸채우기",
      "질문": "저는 _____를 좋아해요.",
      "정답": "ENHYPEN",
      "해설": "정답: ENHYPEN\n이 단어는 문장에서 핵심 정보를 나타냅니다.",
      "원본": "저는 ENHYPEN를 좋아해요."
    },
    {
      "번호": 8,
      "유형": "빈칸채우기",
      "질문": "_____의 새 노래가 나왔어요.",
      "정답": "ENHYPEN",
      "해설": "정답: ENHYPEN\n이 단어는 문장에서 핵심 정보를 나타냅니다.",
      "원본": "ENHYPEN의 새 노래가 나왔어요."
    },
    {
      "번호": 9,
      "유형": "참거짓",
      "질문": "NCT는 2019년에 데뷔했어요.",
      "정답": "참",
      "해설": "제시된 문장은 원문과 동일한 내용입니다.",
      "원본": "NCT는 2019년에 데뷔했어요."
    },
    {
      "번호": 10,
      "유형": "참거짓",
      "질문": "Stray Kids 콘서트에 가고 싶어요.",
      "정답": "거짓",
      "해설": "원문: TWICE 콘서트에 가고 싶어요.\n변경된 부분을 확인하세요.",
      "원본": "TWICE 콘서트에 가고 싶어요."
    }
  ]
}