{
  "level": 1,
  "target_grammar": "-는군요",
  "kpop_references": [
    {
      "group": "BLACKPINK",
      "agency": "YG Entertainment",
      "fandom": "BLINK",
      "concepts": [
        "girl crush",
        "hip-hop",
        "confidence"
      ],
      "members": [
        "Jisoo",
        "Jennie",
        "Rosé",
        "Lisa"
      ]
    }
  ],
  "specified_groups": [
    "BLACKPINK"
  ],
  "critique_summary": [
    {
      "sentence": "BLACKPINK의 노래는 간단히 들으면 좋은 음악이네요.",
      "grammar_ok": false,
      "vocab_ok": true
    },
    {
      "sentence": "가게에 가보니 BLACKPINK의 포스터가 걸려 있는군요.",
      "grammar_ok": true,
      "vocab_ok": true
    },
    {
      "sentence": "한국의 전통 문화는 정말 아름답고 다양하군요.",
      "grammar_ok": true,
      "vocab_ok": true
    }
  ]
}